{"布达拉宫": {"英文名": "Potala Palace", "地址": "西藏自治区拉萨市城关区北京中路35号", "电话": "0891-6339615;400-8649111", "网址": "http://www.potalapalace.cn/", "用时参考": "1-3小时", "交通": "乘8路公车在药王山农贸市场站下车可达；\n若从北京东路出发可步行前往", "门票": "普通票:200人民币 (5月1日-10月31日 周一-周日)\n普通票:100人民币 (11月1日-次年4月30日 周一-周日)\ntips:\n1.2米以下儿童免费；在校学生、残疾人、现役军人、在编教师、老年人可凭有效证件在参观当日购买优惠票；门票预约方式分现场预约和网上购票。\n展开全部>", "开放时间": "09:30-15:00；停止售票时间:15:00；停止入场时间:15:00 (1月1日-12月31日 周一-周日)\ntips:\n参观时间如有变动请关注官网通知"}, "纳木措": {"英文名": "Namtso", "地址": "西藏自治区那曲地区班戈县拉萨市当雄县纳木措自然保护区纳木错湖", "电话": "0891-6110123;0891-6113601;0891-6112759", "用时参考": "1-3小时", "交通": "建议包车；公共交通只能先去当雄县，再从县城租车前往纳木错，比较麻烦费时", "门票": "旺季:120人民币 (5月1日-10月31日 周一-周日)\n淡季:60人民币 (11月1日-次年4月30日 周一-周日)", "开放时间": "全天 (1月1日-12月31日 周一-周日)"}, "大昭寺（已关/暂停营业）": {"英文名": "Jokhang Temple", "地址": "拉萨市城关区八廓西街28号附近大昭寺", "电话": "0891-6336858", "用时参考": "1-3小时", "交通": "乘9、10、11环线、12、15、17、18、19路等公交车在市妇幼保健院站下车可达；乘23、25、28、29路等公交车在措美林站下车可达；\n或从八廓街步行可达", "门票": "普通票:85人民币 (1月1日-12月31日 周一-周日)\ntips:\n大殿内摄影许可90元/张(有些殿内禁止拍摄)；讲解50元/次。", "开放时间": "09:00-18:00,08:00-11:30(信徒开放时间),11:30-17:30(游客开放时间) (1月1日-12月31日 周一-周日)\ntips:\n具体参观时间以导游通知或景区公示为准；团队在大昭寺内整个参观时间不能超过1个小时，其中千佛廊大院内20分钟，中心殿内10分钟，金顶外景拍摄20分钟。"}, "羊卓雍措": {"地址": "西藏自治区山南市贡嘎县307省道附近羊卓雍措", "用时参考": "1-3小时", "交通": "从拉萨往南行100km，约2小时行程，需翻越4990m的岗巴拉山口，可包车或乘班车前往。每天早8:00在拉萨浪卡子办事处有班车发往浪卡子，50元/人。拉萨至日喀则的班车现走新路，不再经过羊湖。所以如欲前往羊湖游览，唯有包车或搭便车，一般包6人吉普车的费用约为1500-2000元/天。此外，在拉萨有很多旅行社组织1日游前往羊湖。", "门票": "免费\ntips:\n以上信息仅供参考，具体票价详情以景区实际公示为准", "开放时间": "08:00-18:30"}, "色拉寺": {"地址": "西藏自治区拉萨市城关区色拉路1号(色拉乌孜山)", "电话": "0891-6383639", "用时参考": "1-3小时", "交通": "乘6、16、24路等公交车在色拉寺站下车可达", "门票": "普通票:50人民币 (1月1日-12月31日 周一-周日)", "开放时间": "09:00-16:00 (1月1日-12月31日 周一-周日)"}}