{
    "apiVersion": "1.0",
    "data": {
        "emotional_prob": 0.7461011364837705,
        "words_freq": {
            "华清宫": 123,
            "骊山": 114,
            "西安": 87,
            "杨贵妃": 81,
            "池子": 72,
            "地方": 66,
            "导游": 63,
            "门票": 60,
            "也是": 57,
            "事变": 57,
            "坐": 54,
            "蒋介石": 54,
            "华清池": 54,
            "没": 51,
            "真": 51,
            "温泉": 48,
            "里": 48,
            "里面": 48,
            "唐玄宗": 48,
            "说": 45,
            "山上": 45,
            "长恨歌": 42,
            "索道": 42,
            "票": 42,
            "历史": 42,
            "杨玉环": 39,
            "景点": 39,
            "中": 39,
            "当年": 39,
            "现在": 36,
            "沐浴": 36,
            "演出": 36,
            "建议": 36,
            "时间": 33,
            "主要": 33,
            "走": 33,
            "请": 33,
            "推荐": 30,
            "表演": 30,
            "在这里": 30,
            "发生": 30,
            "感觉": 30,
            "李隆基": 30,
            "讲解": 30,
            "当时": 27,
            "买": 27,
            "参观": 27,
            "一下": 27,
            "景区": 27,
            "山下": 27,
            "水": 24,
            "皇家": 24,
            "故事": 24,
            "先": 24,
            "享受": 24,
            "皇帝": 24,
            "贵妃": 24,
            "完": 24,
            "上山": 24,
            "刷": 24,
            "唐代": 21,
            "汤池": 21,
            "都是": 21,
            "爱情故事": 21,
            "!": 21,
            "逛": 21,
            "不错": 21,
            "帝王": 21,
            "比较": 21,
            "游客": 21,
            "华清宫，": 21,
            "舞台": 21,
            "几个": 21,
            "挺": 21,
            "累": 21,
            "兵马俑": 21,
            "宫殿": 18,
            "长生殿": 18,
            "觉得": 18,
            "看到": 18,
            "曾经": 18,
            "游": 18,
            "时": 18,
            "洗": 18,
            "团": 18,
            "有点": 18,
            "好像": 18,
            "看看": 18,
            "美，": 18,
            "直接": 18,
            "去过": 18,
            "两个": 18,
            "烽火台": 18,
            "很好": 15,
            "建筑": 15,
            "妃子": 15,
            "建": 15,
            "了解": 15,
            "更": 15,
            "已经": 15,
            "单程": 15,
            "春节": 15,
            "华清": 15,
            "进": 15,
            "遗憾": 15,
            "头发": 15,
            "一定要": 15,
            "一个人": 15,
            "讲": 15,
            "泡": 15,
            "洗澡": 15,
            "出": 15,
            "留下": 15,
            "还能": 15,
            "冬天": 15,
            "一次": 15,
            "，山": 15,
            "太多": 15,
            "缆车": 15,
            "以后": 12,
            "现代": 12,
            "写": 12,
            "著名": 12,
            "晚上": 12,
            "！！": 12,
            "下来": 12,
            "需要": 12,
            "爱情": 12,
            "跟着": 12,
            "旧址": 12,
            "游览": 12,
            "周幽王": 12,
            "唐明皇": 12,
            "用时": 12,
            "学生": 12,
            "泡温泉": 12,
            "留": 12,
            "报": 12,
            "挂": 12,
            "真是": 12,
            "太": 12,
            "一起": 12,
            "听": 12,
            "有意思": 12,
            "然": 12,
            "住": 12,
            "收": 12,
            "挺好": 12,
            "蛮": 12,
            "水，": 12,
            "解说": 12,
            "出浴": 12,
            "上面": 12,
            "遗迹": 12,
            "门口": 12,
            "李世民": 12,
            "旁": 12,
            "越": 12,
            "主题": 12,
            "兵谏亭": 12,
            "一年": 12,
            "往返": 12,
            "第一次": 12,
            "第二次": 12,
            "台阶": 12,
            "2、": 12,
            "上山，": 12,
            "根本": 12,
            "霾": 12,
            "私家车": 12,
            "沾": 12,
            "古代": 9,
            "生活": 9,
            "全程": 9,
            "外面": 9,
            "攻略": 9,
            "值得": 9,
            "文化": 9,
            "现场": 9,
            "120，": 9,
            "便宜": 9,
            "有趣": 9,
            "效果": 9,
            "进行": 9,
            "参考": 9,
            "市区": 9,
            "周一": 9,
            "周日": 9,
            "以下": 9,
            "只能": 9,
            "票价": 9,
            "特别": 9,
            "西安事变，": 9,
            "以前": 9,
            "想": 9,
            "两人": 9,
            "喜欢": 9,
            "之前": 9,
            "间": 9,
            "蜿蜒": 9,
            "渐渐": 9,
            "背景": 9,
            "可以说": 9,
            "整个": 9,
            "回": 9,
            "音乐": 9,
            "眼前": 9,
            "广场": 9,
            "问": 9,
            "讲解员": 9,
            "亭子": 9,
            "过去": 9,
            "听到": 9,
            "每个": 9,
            "一定": 9,
            "东西": 9,
            "带": 9,
            "泡澡": 9,
            "贵": 9,
            "旁边": 9,
            "意思": 9,
            "。华清宫": 9,
            "搜": 9,
            "本来": 9,
            "完美": 9,
            "感受到": 9,
            "介绍": 9,
            "涨": 9,
            "是因为": 9,
            "观看": 9,
            "张学良": 9,
            "湖面": 9,
            "雪花": 9,
            "枝头": 9,
            "唐朝": 9,
            "入浴": 9,
            "专用": 9,
            "后面": 9,
            "不知道": 9,
            "满": 9,
            "拍照": 9,
            "风景": 9,
            "烽火戏诸侯": 9,
            "典故": 9,
            "找": 9,
            "看不到": 9,
            "汤，": 9,
            "停止": 9,
            "下山": 9,
            "树梢": 9,
            "游幸": 9,
            "找到": 9,
            "叫做": 9,
            "五间": 9,
            "厅": 9,
            "车上": 9,
            "不太": 9,
            "池，": 9,
            "游玩": 9,
            "山，": 9,
            "爬山": 9,
            "爬": 9,
            "60元": 9,
            "有兴趣": 9,
            "有必要": 9,
            "对应": 6,
            "乘坐": 6,
            "旅游": 6,
            "上行": 6,
            "一人": 6,
            "骊山，": 6,
            "浪费": 6,
            "电影": 6,
            "一层": 6,
            "一段": 6,
            "片子": 6,
            "形式": 6,
            "总": 6,
            "应该": 6,
            "理解": 6,
            "结束": 6,
            "工作": 6,
            "胜地": 6,
            "西周": 6,
            "完整": 6,
            "历代": 6,
            "遗址": 6,
            "古树": 6,
            "文物": 6,
            "“西安事变”": 6,
            "蜚声": 6,
            "代": 6,
            "http": 6,
            "www": 6,
            "cn": 6,
            "公交": 6,
            "步行": 6,
            "普通": 6,
            "本科": 6,
            "持": 6,
            "身高": 6,
            "众多": 6,
            "外": 6,
            "相当": 6,
            "行": 6,
            "不值": 6,
            "好看": 6,
            "一日游": 6,
            "团，": 6,
            "西安事变": 6,
            "话": 6,
            "等人": 6,
            "确实": 6,
            "捉": 6,
            "玩": 6,
            "一对": 6,
            "注定": 6,
            "寿王": 6,
            "儿媳": 6,
            "封": 6,
            "成": 6,
            "爱": 6,
            "这份": 6,
            "结局": 6,
            "始建于": 6,
            "遍布": 6,
            "执政": 6,
            "悉心": 6,
            "经营": 6,
            "建起": 6,
            "宏大": 6,
            "离宫，": 6,
            "每年": 6,
            "十月": 6,
            "到此": 6,
            "正好": 6,
            "优惠": 6,
            "位": 6,
            "唯美": 6,
            "便": 6,
            "而来": 6,
            "错过": 6,
            "年味": 6,
            "好去处": 6,
            "梦幻": 6,
            "，华清宫": 6,
            "宫灯": 6,
            "灯": 6,
            "璀璨": 6,
            "宛如": 6,
            "灯会": 6,
            "大型": 6,
            "走过": 6,
            "前": 6,
            "精彩": 6,
            "部分": 6,
            "灯光": 6,
            "震撼": 6,
            "热闹": 6,
            "一场": 6,
            "见到": 6,
            "想象": 6,
            "站": 6,
            "澡": 6,
            "晾": 6,
            "拼": 6,
            "最好": 6,
            "时间段": 6,
            "就能": 6,
            "蹭": 6,
            "汤池，": 6,
            "图片": 6,
            "小，": 6,
            "拍": 6,
            "送": 6,
            "朋友": 6,
            "纪念": 6,
            "休闲": 6,
            "古": 6,
            "想要": 6,
            "一众": 6,
            "好多": 6,
            "房子": 6,
            "），": 6,
            "奢侈": 6,
            "当初": 6,
            "之后": 6,
            "雕像": 6,
            "游人": 6,
            "几处": 6,
            "浴池": 6,
            "”。": 6,
            "一派": 6,
            "呈现": 6,
            "枪战": 6,
            "雕塑": 6,
            "浴室": 6,
            "错落": 6,
            "话，": 6,
            "警卫": 6,
            "汤池。": 6,
            "进入": 6,
            "场次": 6,
            "要不要": 6,
            "爬上去": 6,
            "就结束了": 6,
            "冰封": 6,
            "时而": 6,
            "天涯": 6,
            "眼": 6,
            "落": 6,
            "温柔": 6,
            "脚下": 6,
            "年代": 6,
            "打造": 6,
            "最大": 6,
            "流": 6,
            "。华清池": 6,
            "联": 6,
            "理": 6,
            "祝福": 6,
            "讲究": 6,
            "厉害": 6,
            "隔离": 6,
            "发现": 6,
            "之间": 6,
            "见证": 6,
            "腋臭": 6,
            "吹风机": 6,
            "。华": 6,
            "清宫": 6,
            "看点": 6,
            "一部分": 6,
            "免费": 6,
            "讲述": 6,
            "往上": 6,
            "一处": 6,
            "誓台": 6,
            "办公室": 6,
            "激烈": 6,
            "弹孔": 6,
            "装甲": 6,
            "游行": 6,
            "知道": 6,
            "火车站": 6,
            "车": 6,
            "国营": 6,
            "途中": 6,
            "顺道": 6,
            "小时候": 6,
            "父母": 6,
            "，大学": 6,
            "同学": 6,
            "不断": 6,
            "传承": 6,
            "发展": 6,
            "玻璃": 6,
            "子弹": 6,
            "孔": 6,
            "15个": 6,
            "字": 6,
            "恶心": 6,
            "世界上": 6,
            "美事": 6,
            "灯展": 6,
            "节目": 6,
            "不堪": 6,
            "一般般": 6,
            "啦，": 6,
            "价值": 6,
            "很高": 6,
            "国博": 6,
            "。。": 6,
            "飘落": 6,
            "梅花": 6,
            "开": 6,
            "愁！": 6,
            "顺带": 6,
            "适合": 6,
            "深度": 6,
            "住在": 6,
            "宾馆": 6,
            "华清宫：推荐指数：4星": 6,
            "2-3小时": 6,
            "合": 6,
            "二": 6,
            "两次": 6,
            "转": 6,
            "一圈": 6,
            "，缆车": 6,
            "25": 6,
            "忘": 6,
            "支持": 6,
            "现金": 6,
            "结账": 6,
            "记账": 6,
            "想清楚": 6,
            "方案": 6,
            "1、": 6,
            "，刷": 6,
            "一半": 6,
            "侧门": 6,
            "楼梯": 6,
            "走下": 6,
            "屁": 6,
            "永远": 6,
            "不到": 6,
            "头": 6,
            "票，": 6,
            "下山刷": 6,
            "。ps：": 6,
            "别去": 6,
            "荒山": 6,
            "花": 6,
            "一百": 6,
            "游览车": 6,
            "累，": 6,
            "半死": 6,
            "不死心": 6,
            "崩溃": 6,
            "庙": 6,
            "之外": 6,
            "不动": 6,
            "骑马": 6,
            "危": 6,
            "危险": 6,
            "，山上": 6,
            "雾霾": 6,
            "重灾区": 6,
            "天": 6,
            "屈指可数": 6,
            "那几天": 6,
            "天天": 6,
            "售票处": 6,
            "80": 6,
            "送到": 6,
            "后悔": 6,
            "安全": 6,
            "观光车": 6,
            "官方": 6,
            "私导": 6,
            "价钱": 6,
            "没办法": 6,
            "点顾": 6,
            "听听": 6,
            "姿势": 6,
            "弹": 6,
            "孔，": 6,
            "包含": 6,
            "嫌": 6,
            "贵。": 6,
            "10月后": 6,
            "3、": 6,
            "皇气": 6,
            "凉粉": 6,
            "6元": 6,
            "10元": 6,
            "8元": 6,
            "味道": 6,
            "服": 6,
            "下午": 6,
            "少": 6,
            "来回": 6,
            "中国": 3,
            "盛大": 3,
            "建筑群": 3,
            "，兴于": 3,
            "毁于": 3,
            "样子": 3,
            "建国": 3,
            "重修": 3,
            "属于": 3,
            "仿品": 3,
            "照理说": 3,
            "天上": 3,
            "星象": 3,
            "相": 3,
            "最早": 3,
            "唐太宗李世民": 3,
            "紫微星，": 3,
            "自上而下": 3,
            "顺序": 3,
            "水道": 3,
            "相互": 3,
            "贯通": 3,
            "品质": 3,
            "诞生": 3,
            "老公": 3,
            "白居易": 3,
            "先生": 3,
            "一篇": 3,
            "天儿太冷，": 3,
            "两场": 3,
            "同名": 3,
            "古老": 3,
            "改编": 3,
            "而成": 3,
            "露天": 3,
            "舞台剧": 3,
            "一个多小时": 3,
            "尿点": 3,
            "一看": 3,
            "重点": 3,
            "重要": 3,
            "三遍": 3,
            "华清园": 3,
            "！！！！": 3,
            "标志性": 3,
            "标志": 3,
            "马蜂窝": 3,
            "产品": 3,
            "122，": 3,
            "35，": 3,
            "古人": 3,
            "“洗澡池”，哈哈哈。": 3,
            "玄境": 3,
            "6D": 3,
            "四层": 3,
            "仿古": 3,
            "放": 3,
            "故事情节": 3,
            "推敲": 3,
            "emmm": 3,
            "平庸": 3,
            "吹吹打打": 3,
            "！ ": 3,
            "一个女人": 3,
            "战乱": 3,
            "扯淡 ": 3,
            "居住": 3,
            "自古以来": 3,
            "相传": 3,
            "离官": 3,
            "遗留": 3,
            "周、秦": 3,
            "汉、唐、明、清": 3,
            "园林": 3,
            "景观": 3,
            "古建筑": 3,
            "名木": 3,
            "资源": 3,
            "尤": 3,
            "缠绵": 3,
            "震惊": 3,
            "中外": 3,
            "天下": 3,
            "。 ": 3,
            "秦、汉": 3,
            "隋": 3,
            "先后": 3,
            "修建": 3,
            "数次": 3,
            "增建": 3,
            "电话": 3,
            "029": 3,
            "83812003": 3,
            "网址": 3,
            "hqc": 3,
            "1-3小时": 3,
            "交通": 3,
            "306": 3,
            "路": 3,
            "307路": 3,
            "“华清池”站": 3,
            "下车": 3,
            "120": 3,
            "人民币 ": 3,
            "1月1日": 3,
            "12月31日": 3,
            "半票": 3,
            "18周岁": 3,
            "全日制": 3,
            "学生证": 3,
            "免票": 3,
            "1.2米": 3,
            "儿童": 3,
            "65周岁": 3,
            "含": 3,
            "老年人": 3,
            "国家": 3,
            "特殊": 3,
            "津贴": 3,
            "省级": 3,
            "突出": 3,
            "贡献": 3,
            "专家": 3,
            "劳动模": 3,
            "范、": 3,
            "现役军人": 3,
            "残疾人": 3,
            "残疾": 3,
            "军人": 3,
            "有效": 3,
            "证件": 3,
            "开放": 3,
            "07:00-19:00": 3,
            "3月1日": 3,
            "11月30日": 3,
            "07:30-18:00": 3,
            "12月1日": 3,
            "次年": 3,
            "2月28日": 3,
            "城东": 3,
            "60": 3,
            "早": 3,
            "先秦": 3,
            "时期": 3,
            "王公贵戚": 3,
            "宫别": 3,
            "院": 3,
            "华清宫，景区": 3,
            "御汤": 3,
            "文艺": 3,
            "水准": 3,
            "高": 3,
            "入住": 3,
            "酒店": 3,
            "昨天": 3,
            "徒": 3,
            "虚名": 3,
            "名气": 3,
            "高，": 3,
            "一丢": 3,
            "丢": 3,
            "以外": 3,
            "，像": 3,
            "海棠池": 3,
            "全": 3,
            "，干": 3,
            "更好": 3,
            "兵马俑，华清宫，特": 3,
            "告知": 3,
            "169元": 3,
            "深深": 3,
            "坑": 3,
            "家": 3,
            "一个小时": 3,
            "搭建": 3,
            "绝，": 3,
            "，总体还行。": 3,
            "老蒋": 3,
            "真正": 3,
            "一首": 3,
            "诗": 3,
            "男女": 3,
            "生": 3,
            "美丽": 3,
            "动人": 3,
            "很自然": 3,
            "一生": 3,
            "平凡": 3,
            "十七岁时": 3,
            "选中": 3,
            "，嫁": 3,
            "入": 3,
            "皇室": 3,
            "几年": 3,
            "，寿王": 3,
            "母亲": 3,
            "武惠妃": 3,
            "去世": 3,
            "内心": 3,
            "痛苦": 3,
            "焦虑": 3,
            "偶然": 3,
            "机会": 3,
            "，惊鸿": 3,
            "一瞥": 3,
            "窥": 3,
            "容颜": 3,
            "丰韵，阅女": 3,
            "无数": 3,
            "怔": 3,
            "，遂茶不思，饭": 3,
            "，魂": 3,
            "牵梦": 3,
            "绕": 3,
            "接到": 3,
            "后宫": 3,
            "，册": 3,
            "杨贵妃，": 3,
            "纳": 3,
            "新妃，": 3,
            "横刀夺爱": 3,
            "媳妇": 3,
            "相差": 3,
            "30多岁": 3,
            "老夫少妻": 3,
            "儿女": 3,
            "情长": 3,
            "音律": 3,
            "，心": 3,
            "相通": 3,
            "日常生活": 3,
            "恩爱有加": 3,
            "夫妇": 3,
            "爱着": 3,
            "希望": 3,
            "爱吃": 3,
            "爱玩": 3,
            "，爱": 3,
            "，爱发小脾气，": 3,
            "哄": 3,
            "捧": 3,
            "，天真无邪": 3,
            "风情": 3,
            "无限": 3,
            "糊涂": 3,
            "爱，": 3,
            "不顾一切": 3,
            "开辟": 3,
            "几千里": 3,
            "贡道，": 3,
            "小女人": 3,
            "吃": 3,
            "一口": 3,
            "新鲜": 3,
            "荔枝。华清池": 3,
            "共": 3,
            "浴": 3,
            "鸳鸯戏": 3,
            "水。": 3,
            "富家翁": 3,
            "少奶奶": 3,
            "嬉闹终生。安史之乱爆发，狼烟遍地、万马奔腾、": 3,
            "杀声": 3,
            "如潮": 3,
            "马嵬驿": 3,
            "，刀光剑影": 3,
            "背后": 3,
            "生离死": 3,
            "杨贵妃香": 3,
            "消玉殒": 3,
            "黯然神伤": 3,
            "唐肃宗": 3,
            "血腥": 3,
            "崛起": 3,
            "，一路向北，": 3,
            "走向": 3,
            "嬉戏": 3,
            "，绝不会": 3,
            "想到": 3,
            "场": 3,
            "海誓山盟": 3,
            "爱情，": 3,
            "竟是": 3,
            "落魄": 3,
            "凄凉": 3,
            "唐初，背山面渭，": 3,
            "倚": 3,
            "骊峰山": 3,
            "势": 3,
            "筑": 3,
            "，规模宏大，建筑壮丽，楼台馆殿，": 3,
            "幸华清池": 3,
            "合并": 3,
            "骊山景区": 3,
            "120元": 3,
            "108元": 3,
            "30元": 3,
            "不远处": 3,
            "临潼区": 3,
            "同样": 3,
            "精致": 3,
            "花灯": 3,
            "装点": 3,
            "浓浓": 3,
            "节日": 3,
            "喜庆": 3,
            "气氛": 3,
            "踏入": 3,
            "园区": 3,
            "那一刻": 3,
            "迎面": 3,
            "脑海": 3,
            "向往": 3,
            "小桥": 3,
            "流水": 3,
            "人像": 3,
            "破灭": 3,
            "华清宫中楼阁": 3,
            "错落有致": 3,
            "，步道": 3,
            "曲折": 3,
            "镜头": 3,
            "躲避": 3,
            "还算": 3,
            "易如反掌。": 3,
            "换上": 3,
            "简约": 3,
            "汉服": 3,
            "其间": 3,
            "并不": 3,
            "违和": 3,
            "。天色": 3,
            "暗": 3,
            "灯光秀": 3,
            "开启": 3,
            "点亮": 3,
            "、彩": 3,
            "装扮": 3,
            "闪闪发光": 3,
            "水天一色": 3,
            "穿上": 3,
            "华丽": 3,
            "外衣": 3,
            "，炫彩夺目。": 3,
            "第一年": 3,
            "殿宇": 3,
            "红彤彤": 3,
            "灯笼": 3,
            "黄色": 3,
            "花型": 3,
            "吊灯": 3,
            "长廊": 3,
            "映衬": 3,
            "艳": 3,
            "红。立式": 3,
            "唐式": 3,
            "代替": 3,
            "园内": 3,
            "原有": 3,
            "路灯": 3,
            "穿越": 3,
            "盛世": 3,
            "隧道": 3,
            "神秘": 3,
            "宫内": 3,
            "印象": 3,
            "深刻": 3,
            "便是": 3,
            "芙蓉湖": 3,
            "组": 3,
            " “游龙戏": 3,
            "凤”": 3,
            "动态": 3,
            "彩灯": 3,
            "没想到": 3,
            "想起": 3,
            "九龙湖": 3,
            "突然": 3,
            "光彩": 3,
            "照人": 3,
            "高科技": 3,
            "可谓": 3,
            "内外": 3,
            "早就": 3,
            "听闻": 3,
            "大气恢弘、震撼璀璨，": 3,
            "一票": 3,
            "难求": 3,
            "看着": 3,
            "盛景，": 3,
            "由得": 3,
            "发自肺腑": 3,
            "感慨": 3,
            "巨型": 3,
            "史实": 3,
            "投影": 3,
            "星辰": 3,
            "闪闪": 3,
            "皓月当空，": 3,
            "一幅": 3,
            "3D": 3,
            "立体": 3,
            "山水画": 3,
            "两侧": 3,
            "激光柱": 3,
            "动感": 3,
            "声": 3,
            "挥舞": 3,
            "引得": 3,
            "台下": 3,
            "观众们": 3,
            "一同": 3,
            "舞动，": 3,
            "犹如": 3,
            "蹦迪": 3,
            "从没": 3,
            "迪厅": 3,
            "阵势": 3,
            "感染": 3,
            "好想": 3,
            "放飞": 3,
            "自我": 3,
            "走进": 3,
            "人群": 3,
            "狂欢": 3,
            "白天": 3,
            "还在": 3,
            "冬日": 3,
            "嗨": 3,
            "翻": 3,
            "新春": 3,
            "超级": 3,
            "庆幸": 3,
            "过年": 3,
            "这几天": 3,
            "开心": 3,
            "时刻": 3,
            "不容": 3,
            "，略": 3,
            "稍微": 3,
            "汤": 3,
            "原址": 3,
            "逃跑": 3,
            "五间房。": 3,
            "下图": 3,
            "走马观花，": 3,
            "不懂": 3,
            "最实惠": 3,
            "收费": 3,
            "100块": 3,
            "一百块": 3,
            "一齐": 3,
            "人均": 3,
            "20": 3,
            "避开": 3,
            "中午": 3,
            "吃饭": 3,
            "很难": 3,
            "拼成": 3,
            "发": 3,
            "机器": 3,
            "，带": 3,
            "耳麦": 3,
            "专属": 3,
            "频道": 3,
            "小声": 3,
            "听清。": 3,
            "更衣": 3,
            "书上": 3,
            "想着": 3,
            "下去": 3,
            "实物": 3,
            "显得": 3,
            "出口": 3,
            "位置": 3,
            "有文创": 3,
            "店": 3,
            "各种各样": 3,
            "文创产品，琳琅满目，": 3,
            "逛一逛": 3,
            "点": 3,
            "回去": 3,
            "做": 3,
            "华清池景区": 3,
            "就像": 3,
            "度假": 3,
            "山庄": 3,
            "放松": 3,
            "调节": 3,
            "下身心": 3,
            "两三个月": 3,
            "出名": 3,
            "  ": 3,
            "只不过": 3,
            "扔": 3,
            "钱，": 3,
            "一个个": 3,
            "许愿池": 3,
            "墙上": 3,
            "壁画": 3,
            "记录": 3,
            "缠绵悱恻": 3,
            "莫名其妙": 3,
            "财大气粗": 3,
            "一点点": 3,
            "，超": 3,
            "旅": 3,
            "添": 3,
            "一笔": 3,
            "一趟": 3,
            "妃子们": 3,
            "那种": 3,
            "美容": 3,
            "寻思": 3,
            "清幽": 3,
            "显眼": 3,
            "逃": 3,
            "躲": 3,
            "兵士": 3,
            "好久": 3,
            "处": 3,
            "织，": 3,
            "旅行团": 3,
            "导游们": 3,
            "说着": 3,
            "大同小异": 3,
            "不知": 3,
            "是否": 3,
            "过夜半私语": 3,
            "很好看": 3,
            "全息": 3,
            "错过了": 3,
            "一批": 3,
            "进场": 3,
            "离开": 3,
            "枪孔": 3,
            "历历": 3,
            "目，": 3,
            "纸醉金迷": 3,
            "反差": 3,
            "也罢，": 3,
            "青砖": 3,
            "绿叶": 3,
            "红鲤竞": 3,
            "流。": 3,
            "映入": 3,
            "眼帘，": 3,
            "动人心魄": 3,
            "今日": 3,
            "风韵": 3,
            "走入": 3,
            "止": 3,
            "双十二西安事变": 3,
            "惊呆": 3,
            "初中": 3,
            "学习": 3,
            "总是": 3,
            "前因后果，": 3,
            "认真": 3,
            "，原来事变": 3,
            "地点": 3,
            "知识": 3,
            "当天": 3,
            "天气": 3,
            "不错，": 3,
            "旅游团": 3,
            "时间点": 3,
            "人影": 3,
            "蒋委员长": 3,
            "室。": 3,
            "蒋委员长，": 3,
            "得到": 3,
            "登记": 3,
            "候，等待许可。": 3,
            "还没有": 3,
            "房间": 3,
            "一副": 3,
            "矗立": 3,
            "浮想联翩": 3,
            "遗憾的是": 3,
            "尴尬": 3,
            "，景区": 3,
            "安排": 3,
            "。原本以为": 3,
            "1212西安事变": 3,
            "“闭门": 3,
            "不见": 3,
            "背靠": 3,
            "群山": 3,
            "疗养": 3,
            "够": 3,
            "园子": 3,
            "果树": 3,
            "枝繁": 3,
            "叶茂，": 3,
            "果实": 3,
            "累累": 3,
            "安静": 3,
            "氛围": 3,
            "，亭": 3,
            "台水榭，垂柳碧波。华清宫景区": 3,
            "蒋庭": 3,
            "一系列": 3,
            "半山": 3,
            "腰": 3,
            "小姐": 3,
            "姐": 3,
            "天阴": 3,
            "下雨": 3,
            "伞，": 3,
            "拒绝": 3,
            "懒": 3,
            "行程": 3,
            "小时": 3,
            "游记": 3,
            "千年": 3,
            "一瞬": 3,
            "长安梦 饕餮西安红尘中（美食美景——网红新派地道传统人气美食，西安初雪跨年美景旅拍）": 3,
            "mafengwo": 3,
            "i": 3,
            "11626046": 3,
            "html": 3,
            "初雪": 3,
            "午后": 3,
            "融化": 3,
            "淡淡": 3,
            "霜": 3,
            "凝结": 3,
            "枝丫": 3,
            "莲花，": 3,
            " 白玉 ": 3,
            "般": 3,
            "无瑕": 3,
            "湖里": 3,
            "鱼": 3,
            "懒得": 3,
            "动": 3,
            "，静静": 3,
            "趴": 3,
            "扭一扭": 3,
            "尾巴": 3,
            "，笑": 3,
            "颜如花。": 3,
            "亭台": 3,
            "，曳": 3,
            "红裙": 3,
            "倒映": 3,
            "沉鱼惺忪": 3,
            "睡": 3,
            "咫尺": 3,
            "睡莲": 3,
            "人烟": 3,
            "伸出": 3,
            "双手": 3,
            "冰凉": 3,
            "手心": 3,
            "远方": 3,
            "问候": 3,
            "冰晶": 3,
            "绽放": 3,
            "拾起": 3,
            "凉风": 3,
            "回廊": 3,
            "娇羞": 3,
            "久远": 3,
            "浴馆": 3,
            "洗浴": 3,
            "过冬": 3,
            "盛": 3,
            "拿来": 3,
            "观赏": 3,
            "三个": 3,
            "刚": 3,
            "玉像，": 3,
            "欣赏": 3,
            "景致": 3,
            "蓝田玉": 3,
            "原石": 3,
            "材质": 3,
            "有钱": 3,
            "莲花状": 3,
            "一开始": 3,
            "疑惑": 3,
            "为啥": 3,
            "夫妻": 3,
            "二人": 3,
            "男尊女卑，": 3,
            "万千": 3,
            "宠爱于一身": 3,
            "皇上": 3,
            "造": 3,
            "吹": 3,
            "冷": 3,
            "室外": 3,
            "带有": 3,
            "冲浪": 3,
            "按摩": 3,
            "功能": 3,
            "神奇": 3,
            "弄": 3,
            "桑拿房": 3,
            "偏殿，": 3,
            "换衣服": 3,
            "冻": 3,
            "还会": 3,
            "御膳": 3,
            "房": 3,
            "厨子": 3,
            "身边": 3,
            "侍官": 3,
            "显示": 3,
            "皇恩": 3,
            "浩荡": 3,
            "均有": 3,
            "半价": 3,
            "选择": 3,
            "向导": 3,
            "那么多": 3,
            "文字": 3,
            "简介": 3,
            "导": 3,
            "90元": 3,
            "帮": 3,
            "减少": 3,
            "费用": 3,
            "人性化": 3,
            " 盟誓台，那树": 3,
            "树": 3,
            "树上": 3,
            "祈愿": 3,
            "红色": 3,
            "丝带": 3,
            "木牌，": 3,
            "心中": 3,
            "期盼": 3,
            "海棠": 3,
            "汤。 ": 3,
            "赶上": 3,
            "修整": 3,
            "脚手架": 3,
            "浓重": 3,
            "油漆": 3,
            "味，": 3,
            "体验": 3,
            "太子汤、星辰汤": 3,
            "反正": 3,
            "大同": 3,
            "小异": 3,
            "皇帝们": 3,
            "优美": 3,
            "乡，": 3,
            "杀戮": 3,
            "原来": 3,
            "鸳鸯浴。": 3,
            "礼数": 3,
            "管中": 3,
            "窥豹": 3,
            "，穷奢极欲": 3,
            "总算": 3,
            "造成": 3,
            "渔阳鼙鼓动": 3,
            "惊破": 3,
            "霓裳羽衣曲”，": 3,
            "说起": 3,
            "不祥": 3,
            "朝代": 3,
            "更替": 3,
            "大事": 3,
            "，一次又一次演绎，": 3,
            "五年前": 3,
            "相比": 3,
            "却是": 3,
            "变化": 3,
            "门面": 3,
            "宏伟": 3,
            "壮观": 3,
            "摸": 3,
            "触碰": 3,
            "围栏": 3,
            "远远": 3,
            "傍": 3,
            "个人文景点，": 3,
            "透": 3,
            "富丽堂皇": 3,
            "小小": 3,
            "珍贵": 3,
            "宝石": 3,
            "芙蓉园": 3,
            "、芙蓉玉": 3,
            "芙蓉": 3,
            "珍爱，": 3,
            "小字": 3,
            "芙蓉，": 3,
            "亭台楼阁": 3,
            "建造": 3,
            "帝妃": 3,
            "感情": 3,
            "深，": 3,
            "存在": 3,
            "，贵妃": 3,
            "一米": 3,
            "五，": 3,
            "体重": 3,
            "140斤": 3,
            "丰腴": 3,
            "懂": 3,
            "正面": 3,
            "侧面": 3,
            "背面": 3,
            "弧线": 3,
            "……贵妃": 3,
            "酷爱": 3,
            "跳舞": 3,
            "玄宗": 3,
            "就送": 3,
            "海棠汤、莲花": 3,
            "每日": 3,
            "泡汤": 3,
            "～华清池": 3,
            "阴阳": 3,
            "女人": 3,
            "白，": 3,
            "男人": 3,
            "黑": 3,
            "治疗": 3,
            "湿漉漉": 3,
            "，玄宗": 3,
            "抱": 3,
            "爬上": 3,
            "飞霞亭。": 3,
            "晾干": 3,
            "浪漫": 3,
            "感谢": 3,
            "那个年代": 3,
            "记得": 3,
            "十年前": 3,
            "水洗": 3,
            "洗手": 3,
            "服务": 3,
            "仿造": 3,
            "身材": 3,
            "姣好": 3,
            "半": 3,
            "披": 3,
            "浴纱": 3,
            "，足": 3,
            "踩": 3,
            "暖滑": 3,
            "猜": 3,
            "浴。": 3,
            "一点": 3,
            "不好": 3,
            "华清池、九龙湖、五间厅": 3,
            "维修": 3,
            "整体": 3,
            "11月": 3,
            "来年": 3,
            "3月": 3,
            "，华清": 3,
            "池": 3,
            "一共": 3,
            "分": 3,
            "4个": 3,
            "每一个": 3,
            "楼层": 3,
            "上映": 3,
            "看完": 3,
            "人员": 3,
            "带领": 3,
            "影厅": 3,
            "感动": 3,
            "差点": 3,
            "流泪": 3,
            "长相思": 3,
            "，亿长安，": 3,
            "长安": 3,
            "幸福": 3,
            "快乐": 3,
            "call": 3,
            "，风尘仆仆，一进华清宫，": 3,
            "银杏林": 3,
            "惊艳": 3,
            "段": 3,
            "路极": 3,
            "夹道": 3,
            "栽": 3,
            "银杏树": 3,
            "，高": 3,
            "拔，": 3,
            "叶黄": 3,
            "。漫眼望": 3,
            "古朴": 3,
            "楼宇": 3,
            "木叶": 3,
            "浮现": 3,
            "，美不胜": 3,
            "。路": 3,
            "金黄色": 3,
            "树木": 3,
            "美": 3,
            "脱俗。 银杏": 3,
            "色彩": 3,
            "令人": 3,
            "暖心": 3,
            "秋意": 3,
            "渐入": 3,
            "佳境。": 3,
            "阴天，": 3,
            "渲染": 3,
            "金光熠熠，楼台生辉。": 3,
            "青翠": 3,
            "金黄": 3,
            "叶，": 3,
            "垂": 3,
            "天际": 3,
            "交": 3,
            "映": 3,
            "飞舞": 3,
            "半空": 3,
            "坠坠": 3,
            "飞落": 3,
            "地面": 3,
            "厚厚": 3,
            "落叶": 3,
            "铺": 3,
            "金色": 3,
            "地毯": 3,
            "。路过": 3,
            "唐市": 3,
            "红灯笼": 3,
            "高高": 3,
            "悬起": 3,
            "红火": 3,
            "景象": 3,
            "情侣": 3,
            "学子": 3,
            "纷纷": 3,
            "祈福": 3,
            "红丝带": 3,
            "木匾": 3,
            "心愿": 3,
            "秘密": 3,
            "，系": 3,
            "祈祷": 3,
            "。环游华清宫内，亭台楼阁": 3,
            "致，": 3,
            "布局": 3,
            "梨园": 3,
            "区": 3,
            "陈列": 3,
            "大量": 3,
            "器乐": 3,
            "相关": 3,
            "史料": 3,
            "细细": 3,
            "品味": 3,
            "自然": 3,
            "人文": 3,
            "品鉴": 3,
            "感到": 3,
            "尽兴。走马观花，": 3,
            "遗落": 3,
            "美好": 3,
            "封建": 3,
            "宫": 3,
            "也称": 3,
            "“华清池”，": 3,
            "位于": 3,
            " 陕西 省 西安 市 临潼 区。背山面渭，倚骊峰山势而筑，规模宏大，建筑壮丽，楼台馆殿，": 3,
            "。初名“汤泉宫”，": 3,
            "改名": 3,
            "温泉宫": 3,
            "宫，": 3,
            "亦称": 3,
            "骊宫、绣岭宫。华清宫": 3,
            "唐初，": 3,
            "鼎盛": 3,
            "。岁": 3,
            "始还": 3,
            "长安。安史乱后，政局突变，华清宫": 3,
            "迅速": 3,
            "衰落": 3,
            "出游": 3,
            "维修，": 3,
            "解放前": 3,
            "寥落": 3,
            "萧疏。华清池，": 3,
            "解放": 3,
            "人民政府": 3,
            "1959年起": 3,
            "大规模": 3,
            "扩建": 3,
            "华清宫景区": 3,
            "包括": 3,
            "。华清宫西门叫望京门，": 3,
            "进门": 3,
            "芙蓉湖，湖": 3,
            "对面": 3,
            "重建": 3,
            "一座": 3,
            "盟": 3,
            "，盟": 3,
            "棵": 3,
            "连理树，": 3,
            "树干": 3,
            "标注": 3,
            "牌子": 3,
            "1982年": 3,
            "澡堂子": 3,
            "“汤”，": 3,
            "“海棠": 3,
            "汤”，": 3,
            "“春寒": 3,
            "赐浴": 3,
            "华清池，温泉水滑洗凝脂”": 3,
            "行辕": 3,
            "办公": 3,
            "休息": 3,
            "“五间厅”，": 3,
            "顾名思义": 3,
            "秘书室": 3,
            "卧室": 3,
            "会议室": 3,
            "侍从室": 3,
            "主任": 3,
            "墙壁": 3,
            "战斗": 3,
            "桐阴轩（": 3,
            "三间": 3,
            "驻地": 3,
            "五间厅、桐阴轩": 3,
            "昭阳门": 3,
            "徒步": 3,
            "路边": 3,
            "一辆": 3,
            "车。": 3,
            "请愿": 3,
            "内战": 3,
            "一致": 3,
            "抗日": 3,
            "下令": 3,
            "镇压": 3,
            "驱车": 3,
            "赶往": 3,
            "灞桥，": 3,
            "辆": 3,
            "学生们": 3,
            "表示": 3,
            "一周之内": 3,
            "事实": 3,
            "答复": 3,
            "避免": 3,
            "流血": 3,
            "事件": 3,
            "。山": 3,
            "有座": 3,
            "共产党": 3,
            "胡宗南": 3,
            "发起": 3,
            "黄埔军校第七分校": 3,
            "募捐": 3,
            "。兵谏亭": 3,
            "往前走不远，": 3,
            "藏身": 3,
            "角度": 3,
            "右": 3,
            "前方": 3,
            "这块": 3,
            "石头": 3,
            "山体": 3,
            "条": 3,
            "小缝": 3,
            "安装": 3,
            "铁链": 3,
            "方便": 3,
            "攀爬": 3,
            "完全": 3,
            "徒手": 3,
            "分为": 3,
            "有限": 3,
            "强度": 3,
            "爬山。": 3,
            "优质": 3,
            "未必": 3,
            "划分": 3,
            "体现": 3,
            "封建社会": 3,
            "等级": 3,
            "制度": 3,
            "我不知道": 3,
            "，华清池": 3,
            "杨虎城": 3,
            "软禁": 3,
            "场馆": 3,
            "翻新": 3,
            "老照片": 3,
            "供": 3,
            "对照": 3,
            "306路": 3,
            "白色": 3,
            "，记住": 3,
            "好多人": 3,
            "是不是": 3,
            "华清宫兵马俑": 3,
            "5，": 3,
            "坐车": 3,
            "高速": 3,
            "30分钟": 3,
            "乘务员": 3,
            "10月27日以后": 3,
            "长": 3,
            "恨歌": 3,
            "停": 3,
            "放映": 3,
            "感受": 3,
            "课": 3,
            "西安事变”": 3,
            "4D": 3,
            "情节": 3,
            "科技": 3,
            "结合": 3,
            " 。": 3,
            "西安市区": 3,
            "出发": 3,
            "兵马俑、华清池": 3,
            "1日": 3,
            "自由行。华清宫": 3,
            "两": 3,
            "大唐": 3,
            "离宫别苑，": 3,
            "在那里": 3,
            "足以": 3,
            "太宗、": 3,
            "高宗": 3,
            "、明皇": 3,
            "场景": 3,
            "院子": 3,
            "出售": 3,
            "值得一看": 3,
            "继续": 3,
            "老母殿": 3,
            "烽火台。": 3,
            "2小时左右": 3,
            "舞剧": 3,
            "，报": 3,
            "十二": 3,
            "五": 3,
            "上午": 3,
            "工作日": 3,
            "游学": 3,
            "小学生": 3,
            "接": 3,
            "就问": 3,
            "顶，": 3,
            "电瓶": 3,
            "半山，": 3,
            "20元": 3,
            "看了看": 3,
            "爬，": 3,
            "40分钟": 3,
            "死火": 3,
            "高温": 3,
            "熔岩": 3,
            "地下水": 3,
            "形成": 3,
            "，天下": 3,
            "两千七，": 3,
            "数第一。五": 3,
            "挤满": 3,
            "冲着": 3,
            "1小时": 3,
            "观众会": 3,
            "演员们": 3,
            "入座": 3,
            " 西安 事变": 3,
            "力": 3,
            "谏": 3,
            "跪谏": 3,
            "兵谏": 3,
            "心里": 3,
            "活动": 3,
            "布景": 3,
            "生动": 3,
            "2019年6月": 3,
            "『华清宫』，": 3,
            "御": 3,
            "『环园』，": 3,
            "登": 3,
            "『烽火台』。": 3,
            "，白天": 3,
            "吧，": 3,
            "撒子": 3,
            "耍": 3,
            "7:20": 3,
            "有人": 3,
            "拉": 3,
            "绳子": 3,
            "，灯光舞美": 3,
            "马": 3,
            "蜂窝": 3,
            "购演": 3,
            "回程": 3,
            "大巴": 3,
            "车票": 3,
            "骏途旅行网": 3,
            "店铺": 3,
            "咨询": 3,
            "娘娘": 3,
            "傍晚": 3,
            "很多人": 3,
            "剧情": 3,
            "标准": 3,
            "唐太宗": 3,
            "登顶": 3,
            "最高点": 3,
            "相当费": 3,
            "体力": 3,
            "登上": 3,
            "景色": 3,
            "满意": 3,
            "1天": 3,
            "棒": 3
        }
    }
}